compositefk/__init__.py
compositefk/compat.py
compositefk/fields.py
compositefk/related_descriptors.py
m3_django_composite_foreignkey-1.0.5.dist-info/LICENSE
m3_django_composite_foreignkey-1.0.5.dist-info/METADATA
m3_django_composite_foreignkey-1.0.5.dist-info/WHEEL
m3_django_composite_foreignkey-1.0.5.dist-info/top_level.txt
m3_django_composite_foreignkey-1.0.5.dist-info/RECORD
